Metadata-Version: 2.4
Name: dataclass-csv
Version: 1.4.1
Summary: Map CSV data into dataclasses
Project-URL: Homepage, https://github.com/dfurtado/dataclass-csv
Project-URL: Issue Tracker, https://github.com/dfurtado/dataclass-csv/issues
Author: Daniel Furtado
License-File: AUTHORS.md
License-File: LICENSE
Keywords: csv,dataclass,dataclass-csv,dataclasses
Classifier: Development Status :: 5 - Production/Stable
Classifier: Environment :: Console
Classifier: Intended Audience :: Developers
Classifier: License :: OSI Approved :: BSD License
Classifier: Natural Language :: English
Classifier: Operating System :: MacOS :: MacOS X
Classifier: Operating System :: Microsoft :: Windows
Classifier: Operating System :: POSIX
Classifier: Operating System :: Unix
Classifier: Programming Language :: Python :: 3 :: Only
Classifier: Programming Language :: Python :: 3.7
Classifier: Programming Language :: Python :: 3.8
Classifier: Programming Language :: Python :: 3.9
Classifier: Programming Language :: Python :: 3.10
Classifier: Programming Language :: Python :: 3.11
Classifier: Programming Language :: Python :: 3.12
Classifier: Programming Language :: Python :: 3.13
Requires-Python: >=3.7
